featurehub_sdk/__init__.py
featurehub_sdk/client_context.py
featurehub_sdk/edge_service.py
featurehub_sdk/featurehub_config.py
featurehub_sdk/featurehub_repository.py
featurehub_sdk/fh_state_base_holder.py
featurehub_sdk/interceptors.py
featurehub_sdk/polling_edge_service.py
featurehub_sdk/strategy_attribute_country_name.py
featurehub_sdk/strategy_attribute_device_name.py
featurehub_sdk/strategy_attribute_platform_name.py
featurehub_sdk/strategy_matchers.py
featurehub_sdk/streaming_edge_service.py
featurehub_sdk/version.py
featurehub_sdk-1.0.0.dist-info/LICENSE
featurehub_sdk-1.0.0.dist-info/METADATA
featurehub_sdk-1.0.0.dist-info/WHEEL
featurehub_sdk-1.0.0.dist-info/top_level.txt
featurehub_sdk-1.0.0.dist-info/RECORD
