Metadata-Version: 2.1
Name: featurehub-sdk
Version: 1.0.0
Summary: Official Python SDK for FeatureHub
Home-page: https://github.com/featurehub-io/featurehub-python-sdk
Author: FeatureHub.io
Author-email: info@featurehub.io
License: MIT
Keywords: feature-flags,feature-toggles,flags,toggles
License-File: LICENSE
Requires-Dist: urllib3 (==1.26.*)
Requires-Dist: sseclient-py (==1.7.*)
Requires-Dist: murmurhash2 (==0.2.*)
Requires-Dist: node-semver (==0.8.*)
